single_doc_retrieval/__init__.py
single_doc_retrieval/config.py
single_doc_retrieval/core.py
single_doc_retrieval/data_utils.py
single_doc_retrieval/embedding_utils.py
single_doc_retrieval/prompts.py
single_doc_retrieval-0.2.0.dist-info/licenses/LICENSE
single_doc_retrieval-0.2.0.dist-info/METADATA
single_doc_retrieval-0.2.0.dist-info/WHEEL
single_doc_retrieval-0.2.0.dist-info/top_level.txt
single_doc_retrieval-0.2.0.dist-info/RECORD
