Metadata-Version: 2.4
Name: single_doc_retrieval
Version: 0.2.0
Summary: A retrieval pipeline for single documents.
Home-page: 
Author: Vahan Martirosyan
Author-email: vahan@kiwidata.com
Classifier: Programming Language :: Python :: 3
Classifier: License :: OSI Approved :: MIT License
Classifier: Operating System :: OS Independent
Requires-Python: >=3.10
License-File: LICENSE
Requires-Dist: openai
Requires-Dist: numpy
Dynamic: author
Dynamic: author-email
Dynamic: classifier
Dynamic: description
Dynamic: description-content-type
Dynamic: license-file
Dynamic: requires-dist
Dynamic: requires-python
Dynamic: summary
